aguy11/__init__.py
aguy11/main.py
aguy11-1.0.1.dist-info/LICENSE
aguy11-1.0.1.dist-info/METADATA
aguy11-1.0.1.dist-info/WHEEL
aguy11-1.0.1.dist-info/top_level.txt
aguy11-1.0.1.dist-info/zip-safe
aguy11-1.0.1.dist-info/RECORD
