Metadata-Version: 2.1
Name: aguy11
Version: 1.0.1
Summary: Module for finding cool and useful stuff quickly
Home-page: UNKNOWN
Author: aguy11
Author-email: aguy11@guerrillamail.org
License: MIT License
Platform: UNKNOWN
Classifier: Programming Language :: Python :: 3
Classifier: License :: OSI Approved :: MIT License
Classifier: Operating System :: OS Independent
Requires-Python: >=3.0
